trulens/benchmark/__init__.py
trulens/benchmark/benchmark_frameworks/__init__.py
trulens/benchmark/benchmark_frameworks/dataset/beir_loader.py
trulens/benchmark/benchmark_frameworks/experiments/competitive_analysis.ipynb
trulens/benchmark/benchmark_frameworks/experiments/context_relevance/trec_dl_passage_relevance_judges.ipynb
trulens/benchmark/benchmark_frameworks/experiments/dataset_preprocessing.py
trulens/benchmark/benchmark_frameworks/experiments/groundedness/llm_aggrefact_groundedness_benchmark.ipynb
trulens/benchmark/benchmark_frameworks/experiments/rag_triad_baselines.ipynb
trulens/benchmark/benchmark_frameworks/meta_evaluation_examples.ipynb
trulens/benchmark/benchmark_frameworks/tru_benchmark_experiment.py
trulens/benchmark/generate/__init__.py
trulens/benchmark/generate/generate_test_set.py
trulens/benchmark/groundedness_benchmark.ipynb
trulens/benchmark/groundedness_benchmark_abstentions.ipynb
trulens/benchmark/test_cases.py
trulens_benchmark-2.5.3.dist-info/METADATA
trulens_benchmark-2.5.3.dist-info/WHEEL
trulens_benchmark-2.5.3.dist-info/RECORD
